qiita_py_nn/__init__.py
qiita_py_nn/classes.py
qiita_py_nn/client.py
qiita_py_nn/client2.py
qiita_py_nn/client_base.py
qiita_py_nn/exception.py
qiita_py_nn/response.py
qiita_py_nn-1.0.dist-info/METADATA
qiita_py_nn-1.0.dist-info/WHEEL
qiita_py_nn-1.0.dist-info/top_level.txt
qiita_py_nn-1.0.dist-info/RECORD
