Metadata-Version: 2.4
Name: qiita_py_nn
Version: 1.0
Summary: Python Wrapper for Qiita API v2
Home-page: https://github.com/nekoniii3/qiita_py_nn
Author: nekoniii3
Author-email: nekonii3.dev@gmail.com
License: MIT
Platform: any
Classifier: Environment :: Web Environment
Classifier: Intended Audience :: Developers
Classifier: Operating System :: OS Independent
Classifier: Programming Language :: Python
Classifier: Topic :: Software Development
Requires-Dist: pyyaml
Requires-Dist: requests
Dynamic: author
Dynamic: author-email
Dynamic: classifier
Dynamic: description
Dynamic: home-page
Dynamic: license
Dynamic: platform
Dynamic: requires-dist
Dynamic: summary
